ebmlite/__init__.py
ebmlite/core.py
ebmlite/decoding.py
ebmlite/encoding.py
ebmlite/threaded_file.py
ebmlite/util.py
ebmlite/xml_codecs.py
ebmlite/schemata/__init__.py
ebmlite/schemata/matroska.xml
ebmlite/schemata/mide_config_ui.xml
ebmlite/schemata/mide_ide.xml
ebmlite/schemata/mide_manifest.xml
ebmlite/tools/__init__.py
ebmlite/tools/ebml2xml.py
ebmlite/tools/list_schemata.py
ebmlite/tools/utils.py
ebmlite/tools/view_ebml.py
ebmlite/tools/xml2ebml.py
ebmlite-3.4.1.dist-info/licenses/LICENSE
tests/__init__.py
tests/test_codecs.py
tests/test_core.py
tests/test_decode.py
tests/test_encode.py
tests/test_general.py
tests/test_tools.py
tests/module_path_testing/__init__.py
ebmlite-3.4.1.dist-info/METADATA
ebmlite-3.4.1.dist-info/WHEEL
ebmlite-3.4.1.dist-info/entry_points.txt
ebmlite-3.4.1.dist-info/top_level.txt
ebmlite-3.4.1.dist-info/RECORD
